README.txt
setup.py
collective/__init__.py
collective.advancedsearchtamer.egg-info/PKG-INFO
collective.advancedsearchtamer.egg-info/SOURCES.txt
collective.advancedsearchtamer.egg-info/dependency_links.txt
collective.advancedsearchtamer.egg-info/entry_points.txt
collective.advancedsearchtamer.egg-info/namespace_packages.txt
collective.advancedsearchtamer.egg-info/not-zip-safe
collective.advancedsearchtamer.egg-info/requires.txt
collective.advancedsearchtamer.egg-info/top_level.txt
collective/advancedsearchtamer/__init__.py
collective/advancedsearchtamer/configure.zcml
collective/advancedsearchtamer/tests.py
collective/advancedsearchtamer/version.txt
collective/advancedsearchtamer/browser/__init__.py
collective/advancedsearchtamer/browser/configure.zcml
collective/advancedsearchtamer/browser/js/search.js
collective/advancedsearchtamer/profiles/default/jsregistry.xml
docs/HISTORY.txt