Metadata-Version: 1.0
Name: collective.advancedsearchtamer
Version: 1.0
Summary: Tries to tame Plone's advanced search form
Home-page: UNKNOWN
Author: Netsight Internet Solutions
Author-email: support@netsight.co.uk
License: GPL
Keywords: plone search
Platform: UNKNOWN
Classifier: Programming Language :: Python
Classifier: Topic :: Software Development :: Libraries :: Python Modules
